[
  {
    "id": "2048",
    "title": "2048",
    "category": "Puzzle",
    "thumbnail": "https://picsum.photos/seed/2048/400/300",
    "iframeUrl": "https://play2048.co/"
  },
  {
    "id": "hextris",
    "title": "Hextris",
    "category": "Arcade",
    "thumbnail": "https://picsum.photos/seed/hextris/400/300",
    "iframeUrl": "https://hextris.io/"
  },
  {
    "id": "flappy-bird",
    "title": "Flappy Bird",
    "category": "Arcade",
    "thumbnail": "https://picsum.photos/seed/flappy/400/300",
    "iframeUrl": "https://flappybird.io/"
  },
  {
    "id": "snake",
    "title": "Snake",
    "category": "Classic",
    "thumbnail": "https://picsum.photos/seed/snake/400/300",
    "iframeUrl": "https://www.google.com/logos/2010/pacman10-i.html"
  },
  {
    "id": "tetris",
    "title": "Tetris",
    "category": "Classic",
    "thumbnail": "https://picsum.photos/seed/tetris/400/300",
    "iframeUrl": "https://tetris.com/play-tetris"
  },
  {
    "id": "sudoku",
    "title": "Sudoku",
    "category": "Puzzle",
    "thumbnail": "https://picsum.photos/seed/sudoku/400/300",
    "iframeUrl": "https://www.sudoku.com/"
  }
]
